csh256/__init__.py
csh256/__main__.py
csh256/_csh256.c
csh256/_csh256.cpython-39-x86_64-linux-gnu.so
csh256/_version.py
csh256/core.py
csh256/utils.py
csh256-1.0.6.dist-info/METADATA
csh256-1.0.6.dist-info/WHEEL
csh256-1.0.6.dist-info/entry_points.txt
csh256-1.0.6.dist-info/top_level.txt
csh256-1.0.6.dist-info/RECORD
csh256-1.0.6.dist-info/licenses/LICENSE
