Metadata-Version: 2.4
Name: csh256
Version: 1.0.6
Summary: CSH-256: A hybrid password hashing algorithm with time-cost resistance
Author-email: Ibrahim Hilal Aboukila <ibrahemabokila@gmail.com>
License: MIT License
Project-URL: Homepage, https://github.com/hemaabokila/CSH-256-Repo
Project-URL: Documentation, https://github.com/hemaabokila/CSH-256-Repo#readme
Project-URL: Repository, https://github.com/hemaabokila/CSH-256-Repo
Project-URL: Bug Tracker, https://github.com/hemaabokila/CSH-256-Repo/issues
Keywords: password,hashing,cryptography,security,csh256,pbkdf
Classifier: Development Status :: 4 - Beta
Classifier: Intended Audience :: Developers
Classifier: Topic :: Security :: Cryptography
Classifier: Programming Language :: Python :: 3
Classifier: Programming Language :: Python :: 3.8
Classifier: Programming Language :: Python :: 3.9
Classifier: Programming Language :: Python :: 3.10
Classifier: Programming Language :: Python :: 3.11
Classifier: Programming Language :: Python :: 3.12
Classifier: Programming Language :: C
Requires-Python: >=3.8
License-File: LICENSE
Provides-Extra: dev
Requires-Dist: pytest>=7.0; extra == "dev"
Requires-Dist: pytest-benchmark>=4.0; extra == "dev"
Requires-Dist: black>=23.0; extra == "dev"
Requires-Dist: mypy>=1.0; extra == "dev"
Requires-Dist: flake8>=6.0; extra == "dev"
Provides-Extra: docs
Requires-Dist: sphinx>=5.0; extra == "docs"
Requires-Dist: sphinx-rtd-theme>=1.0; extra == "docs"
Dynamic: license-file
